tslib/__init__.py
tslib/version.py
tslib-1.8.dist-info/LICENSE
tslib-1.8.dist-info/METADATA
tslib-1.8.dist-info/WHEEL
tslib-1.8.dist-info/entry_points.txt
tslib-1.8.dist-info/pbr.json
tslib-1.8.dist-info/top_level.txt
tslib-1.8.dist-info/zip-safe
tslib-1.8.dist-info/RECORD
