Metadata-Version: 2.1
Name: tslib
Version: 1.8
Summary: A library for dealing with human-readable time offsets and timestamps
Home-page: https://github.com/mpetazzoni/tslib
Author: Maxime Petazzoni
Author-email: maxime.petazzoni@bulix.org
License: Apache Software License v2
Platform: UNKNOWN
Classifier: Operating System :: OS Independent
Classifier: Programming Language :: Python
Requires-Dist: pytz
Requires-Dist: six
